maruval/__init__.py
maruval/atom.py
maruval/jq.py
maruval/marufind.py
maruval/marusearch.py
maruval/maruval.py
maruval-1.0.1.data/data/schemata/audioComponent.json
maruval-1.0.1.data/data/schemata/chapter.json
maruval-1.0.1.data/data/schemata/character.json
maruval-1.0.1.data/data/schemata/checkboxExercise.json
maruval-1.0.1.data/data/schemata/contentNotes.json
maruval-1.0.1.data/data/schemata/dateExercise.json
maruval-1.0.1.data/data/schemata/dialog.json
maruval-1.0.1.data/data/schemata/dialogResponse.json
maruval-1.0.1.data/data/schemata/dialogSpeech.json
maruval-1.0.1.data/data/schemata/imageComponent.json
maruval-1.0.1.data/data/schemata/importconfig.json
maruval-1.0.1.data/data/schemata/linkComponent.json
maruval-1.0.1.data/data/schemata/mail.json
maruval-1.0.1.data/data/schemata/notebookEntry.json
maruval-1.0.1.data/data/schemata/page.json
maruval-1.0.1.data/data/schemata/pageTransition.json
maruval-1.0.1.data/data/schemata/process-palette.json
maruval-1.0.1.data/data/schemata/radioButtonExercise.json
maruval-1.0.1.data/data/schemata/textComponent.json
maruval-1.0.1.data/data/schemata/textExercise.json
maruval-1.0.1.data/data/schemata/topic.json
maruval-1.0.1.data/data/schemata/uploadExercise.json
maruval-1.0.1.data/data/schemata/videoComponent.json
maruval-1.0.1.data/scripts/marufind
maruval-1.0.1.data/scripts/marupretty
maruval-1.0.1.data/scripts/marusearch
maruval-1.0.1.data/scripts/maruval
maruval-1.0.1.dist-info/LICENSE
maruval-1.0.1.dist-info/METADATA
maruval-1.0.1.dist-info/WHEEL
maruval-1.0.1.dist-info/top_level.txt
maruval-1.0.1.dist-info/RECORD
