Metadata-Version: 2.1
Name: maruval
Version: 1.0.1
Summary: Validator for marugoto game content
Home-page: http://github.com/uzh/maruval
Author: Danny McDonald
Author-email: daniel.mcdonald@uzh.ch
License: MIT
Platform: UNKNOWN
Requires-Dist: jsonschema (==3.0.1)
Requires-Dist: setuptools
